{"sections":{"1655884680cc9a832b":{"type":"icons-block","settings":{"feature_block_id":"cf729b6f-5ee2-43fa-ba0c-14213b82f683"}},"main":{"type":"list-collections-template","settings":{"title_enable":true,"display_type":"all","sort":"products_high","grid":"4"}},"logo-list":{"type":"logo-list","disabled":true,"blocks":{"logo1":{"type":"logo_image","settings":{"link":""}},"logo2":{"type":"logo_image","settings":{"link":""}},"logo3":{"type":"logo_image","settings":{"link":""}},"logo4":{"type":"logo_image","settings":{"link":""}},"logo5":{"type":"logo_image","settings":{"link":""}},"logo6":{"type":"logo_image","settings":{"link":""}}},"block_order":["logo1","logo2","logo3","logo4","logo5","logo6"],"settings":{"title":"Our brands","logo_opacity":76,"divider":false}}},"order":["1655884680cc9a832b","main","logo-list"]}